<Alloy>
   <Window class="container">
      <View id="contenedorGeneral">
         <Label id="usuarioLabel" class="loginLabel" text="Usuario:"></Label>
         <View class="contenedorElemtos">
            <TextField id="usuarioField"  class="loginField" value=""/>
         </View>
         <Label id="contrase単aLabel" class="loginLabel" text="Contrase単a:"></Label>
         <View class="contenedorElemtos">
            <TextField id="contrase単aField" class="loginField" value="" />
         </View>
         <View id="contenedorEntrar">
            <Button id="botonEntrar" class="logEntrarButton"  onClick="entrar" title="Entrar"></Button>
         </View>
         <View id="contenedorCrear">
            <Button id="botonEntrar" class="logEntrarButton"  onClick="crear" title="Crear Usuario"></Button>
         </View>
         <View id="contenedorRecuperar">
            <Button id="botonRecuperar" class="logEntrarButton"  onClick="recuperar" title="Recuperar Contrase単a"></Button>
         </View>
      </View>
   </Window>
</Alloy>
